setup.py
torasync/__init__.py
torasync/torasync.py
torasync.egg-info/PKG-INFO
torasync.egg-info/SOURCES.txt
torasync.egg-info/dependency_links.txt
torasync.egg-info/requires.txt
torasync.egg-info/top_level.txt