Metadata-Version: 1.0
Name: torasync
Version: 0.0.0.1
Summary: Run task asynchronously in other processes in easy way
Home-page: https://github.com/ipconfiger/torasync
Author: Alexander.Li
Author-email: superpowerlee@gmail.com
License: LGPL
Keywords: tornado asynchronous multiprocess
Platform: UNKNOWN
